wanda/__init__.py
wanda/sources/__init__.py
wanda/sources/earthview_ids.py
wanda/sources/extractor.py
wanda/sources/generator/__init__.py
wanda/sources/generator/gradient1.py
wanda/sources/generator/gradient2.py
wanda/sources/generator/honeycomb.py
wanda/sources/generator/scheme.py
wanda/sources/generator/tiles.py
wanda/utils/__init__.py
wanda/utils/common_utils.py
wanda/utils/image_utils.py
wanda/utils/os_utils.py
wanda/wanda.py
wanda-1.0.0.dist-info/LICENSE
wanda-1.0.0.dist-info/METADATA
wanda-1.0.0.dist-info/WHEEL
wanda-1.0.0.dist-info/entry_points.txt
wanda-1.0.0.dist-info/RECORD
