Metadata-Version: 2.1
Name: wanda
Version: 1.0.0
Summary: Set wallpapers with keywords or randomly
Home-page: https://github.com/ksh-b/wanda
License: MIT
Keywords: wallpaper,reddit,wallhaven,earthview,termux
Author: kshib
Author-email: ksyko@pm.me
Requires-Python: >=3.8,<4.0
Classifier: License :: OSI Approved :: MIT License
Classifier: Programming Language :: Python :: 3
Classifier: Programming Language :: Python :: 3.8
Classifier: Programming Language :: Python :: 3.9
Classifier: Programming Language :: Python :: 3.10
Classifier: Programming Language :: Python :: 3.11
Classifier: Programming Language :: Python :: 3.12
Requires-Dist: Pillow (>=10.3.0,<11.0.0)
Requires-Dist: appdirs (>=1.4.4,<2.0.0)
Requires-Dist: cloudscraper (>=1.2.71,<2.0.0)
Requires-Dist: colorthief (>=0.2.1,<0.3.0)
Requires-Dist: filetype (>=1.2.0,<2.0.0)
Requires-Dist: lxml (>=5.2.2,<6.0.0)
Requires-Dist: musicbrainzngs (>=0.7.1,<0.8.0)
Requires-Dist: screeninfo (>=0.8.1,<0.9.0)
Project-URL: Bug Tracker, https://github.com/ksh-b/wanda/issues
Project-URL: Repository, https://github.com/ksh-b/wanda
